merge_kdbx/__init__.py
merge_kdbx/clparser.py
merge_kdbx/kdbx_xml_util.py
merge_kdbx/merge_kdbx.py
merge_kdbx-0.0.3.dist-info/METADATA
merge_kdbx-0.0.3.dist-info/WHEEL
merge_kdbx-0.0.3.dist-info/entry_points.txt
merge_kdbx-0.0.3.dist-info/top_level.txt
merge_kdbx-0.0.3.dist-info/RECORD
