Metadata-Version: 2.1
Name: merge-kdbx
Version: 0.0.3
Summary: A mergetool for Keepass 2.x databases
Home-page: https://github.com/RollMan/merge_kdbx
Author: rollman054
Author-email: qwpmb554@gmail.com
License: UNKNOWN
Platform: UNKNOWN
Classifier: Programming Language :: Python :: 3
Classifier: Operating System :: OS Independent
